<?xml version="1.0" encoding="utf-8" ?><dwsync><file name="index.html" server="www.awkwardturtlemedia.com" local="3433107170" remote="16318012608" /><file name="index.html" server="www.awkwardturtlemedia.com/public_html/" local="3438661897" remote="16323567348" /><file name=".DS_Store" server="www.awkwardturtlemedia.com/public_html/" local="3435522305" remote="12025476692" /><file name="rearrange logo copy.jpg" server="www.awkwardturtlemedia.com/public_html/" local="3433991538" remote="12025476872" /><file name="testlogo.jpg" server="www.awkwardturtlemedia.com/public_html/" local="3434600781" remote="12025476872" /><file name="green.jpg" server="www.awkwardturtlemedia.com/public_html/" local="3434602604" remote="16333637088" /><file name="gray.jpg" server="www.awkwardturtlemedia.com/public_html/" local="3434603236" remote="16333637088" /><file name="contact.html" server="www.awkwardturtlemedia.com/public_html/" local="3452353337" remote="16337258748" /><file name="videos.html" server="www.awkwardturtlemedia.com/public_html/" local="3441674080" remote="16333636248" /><file name="pricing.html" server="www.awkwardturtlemedia.com/public_html/" local="3441669140" remote="16326575748" /><file name="vendors.html" server="www.awkwardturtlemedia.com/public_html/" local="3441669027" remote="16326575748" /><file name="about.html" server="www.awkwardturtlemedia.com/public_html/" local="3441669040" remote="16333636368" /><file name="blog.html" server="www.awkwardturtlemedia.com/public_html/" local="3441669040" remote="16333636368" /><file name="ajaxSubmit.php" server="www.awkwardturtlemedia.com/public_html/" local="3435728154" remote="16346281008" /><file name="testpage.html" server="www.awkwardturtlemedia.com/public_html/" local="3435707133" remote="16320612588" /><file name="googlea4d7a581ba52270b.html" server="www.awkwardturtlemedia.com/public_html/" local="3436151733" remote="16321057248" /></dwsync>